<?xml version="1.0" encoding="utf-8"?>
<LanguageData>
  <!--The following translations were generated by https://www.deepl.com/-->
  <!-- EN: TC Chip Fabrication -->
  <CGearChipStand.label>Изготовление микросхем TC</CGearChipStand.label>
  <!-- EN: A stand equipped with all the tools required to make Tactical Charged (TC) Chips. -->
  <CGearChipStand.description>Стенд, оснащенный всеми необходимыми инструментами для изготовления тактических заряженных чипов (TC).</CGearChipStand.description>
  <!-- EN: TC Weapons Bench -->
  <TableCGear.label>Оружейная скамья TC</TableCGear.label>
  <!-- EN: A workbench equipped with all the tools required to make Tactical Charged (TC) Gear. -->
  <TableCGear.description>Верстак, оснащенный всеми необходимыми инструментами для изготовления Tactical Charged (TC) Gear.</TableCGear.description>
  <!-- EN: TC Tool Cabinet -->
  <TCToolCabinet.label>TC Tool Cabinet</TCToolCabinet.label>
  <!-- EN: Advanced tool box with power tools that improves work speed when placed near a workbench. -->
  <TCToolCabinet.description>Продвинутый ящик с электроинструментами, который повышает скорость работы, если его поместить рядом с верстаком.</TCToolCabinet.description>
</LanguageData>
